tools_zy/__init__.py
tools_zy/convData.py
tools_zy/splitData.py
tools_zy/utils.py
tools_zy-0.1.8.1.dist-info/LICENSE
tools_zy-0.1.8.1.dist-info/METADATA
tools_zy-0.1.8.1.dist-info/WHEEL
tools_zy-0.1.8.1.dist-info/top_level.txt
tools_zy-0.1.8.1.dist-info/RECORD
