Metadata-Version: 2.2
Name: tools-zy
Version: 0.1.8.1
Summary: Some tools for AI model training and inference.
Home-page: https://github.com/wzy-777/tools_zy
Author: Zhiyuan Wang
Author-email: WangZhiyuan@mail.ustc.edu.cn
Classifier: Programming Language :: Python :: 3
Classifier: License :: OSI Approved :: MIT License
Classifier: Operating System :: OS Independent
Requires-Python: >=3.10
License-File: LICENSE
Requires-Dist: numpy>=1.14.4
Requires-Dist: tqdm>=4.0.0
Requires-Dist: opencv-python>=4.5.1
Dynamic: author
Dynamic: author-email
Dynamic: classifier
Dynamic: description
Dynamic: description-content-type
Dynamic: home-page
Dynamic: requires-dist
Dynamic: requires-python
Dynamic: summary
